README.md
setup.py
cxw/__init__.py
cxw.egg-info/PKG-INFO
cxw.egg-info/SOURCES.txt
cxw.egg-info/dependency_links.txt
cxw.egg-info/requires.txt
cxw.egg-info/top_level.txt